pydantic_br/__init__.py
pydantic_br/field_errors.py
pydantic_br/fields/base_field.py
pydantic_br/fields/base_field_v2.py
pydantic_br/fields/certidao_field.py
pydantic_br/fields/cnh_field.py
pydantic_br/fields/cnpj_field.py
pydantic_br/fields/cpf_field.py
pydantic_br/fields/pis_field.py
pydantic_br/fields/te_field.py
pydantic_br/get_versions.py
pydantic_br/validators/base_validator.py
pydantic_br/validators/certidao_validator.py
pydantic_br/validators/cnh_validator.py
pydantic_br/validators/cnpj_validator.py
pydantic_br/validators/cpf_validator.py
pydantic_br/validators/pis_validator.py
pydantic_br/validators/te_validator.py
pydantic_br-1.0.1.dist-info/LICENSE
pydantic_br-1.0.1.dist-info/METADATA
pydantic_br-1.0.1.dist-info/WHEEL
pydantic_br-1.0.1.dist-info/RECORD
