Metadata-Version: 2.1
Name: pydantic-br
Version: 1.0.1
Summary: Pydantic library extension with Brazilian fields
Home-page: https://github.com/scjorge/pydantic_br
License: MIT
Keywords: pydantic,json,json-schema,hints,parsin,brasil,documentos,br,fastapi,doc,documento,schema
Author: Jorge Silva
Author-email: jorgesilva.ti@hotmail.com
Maintainer: Jorge Silva
Maintainer-email: jorgesilva.ti@hotmail.com
Requires-Python: >=3.8.1,<4.0.0
Classifier: Framework :: FastAPI
Classifier: Framework :: Pydantic
Classifier: Intended Audience :: Developers
Classifier: Intended Audience :: Information Technology
Classifier: License :: OSI Approved :: MIT License
Classifier: Natural Language :: Portuguese
Classifier: Programming Language :: Python :: 3
Classifier: Programming Language :: Python :: 3.9
Classifier: Programming Language :: Python :: 3.10
Classifier: Programming Language :: Python :: 3.11
Project-URL: Documentation, https://pydantic-br.readthedocs.io
Project-URL: Repository, https://github.com/scjorge/pydantic_br
